LICENSE.rst
MANIFEST.in
README.rst
setup.cfg
setup.py
dtool_s3/__init__.py
dtool_s3/storagebroker.py
dtool_s3.egg-info/PKG-INFO
dtool_s3.egg-info/SOURCES.txt
dtool_s3.egg-info/dependency_links.txt
dtool_s3.egg-info/entry_points.txt
dtool_s3.egg-info/requires.txt
dtool_s3.egg-info/top_level.txt