Metadata-Version: 1.1
Name: dtool-s3
Version: 0.1.0
Summary: Add S3 support to dtool
Home-page: https://github.com/jic-dtool/dtool-s3
Author: Tjelvar Olsson
Author-email: tjelvar.olsson@jic.ac.uk
License: MIT
Download-URL: https://github.com/jic-dtool/dtool-s3/tarball/0.1.0
Platform: UNKNOWN
